tinyinject/__init__.py
tinyinject/context.py
tinyinject/di.py
tinyinject/registry.py
tinyinject/require.py
tinyinject-0.4.0.dist-info/LICENSE
tinyinject-0.4.0.dist-info/METADATA
tinyinject-0.4.0.dist-info/WHEEL
tinyinject-0.4.0.dist-info/top_level.txt
tinyinject-0.4.0.dist-info/RECORD
