Metadata-Version: 2.1
Name: tinyinject
Version: 0.4.0
Summary: A minimalistic dependency injection framework
Author-email: Krzysztof Stronka <stronka.k@gmail.com>
License: MIT
Project-URL: Homepage, https://github.com/stronka/tinyinject
Project-URL: Repository, https://github.com/stronka/tinyinject
Requires-Python: >=3.10
License-File: LICENSE
